Workbook

Sheet Summary
A1: Selected scenario: | B1: =Assumptions!B2
B3: Year 1 | C3: Year 2 | D3: Year 3
A4: New free sign-ups | B4: =SUMIF(Monthly!$B$2:$B$37,1,Monthly!D$2:D$37) | C4: =SUMIF(Monthly!$B$2:$B$37,2,Monthly!D$2:D$37) | D4: =SUMIF(Monthly!$B$2:$B$37,3,Monthly!D$2:D$37)
A5: Subscription revenue | B5: =SUMIF(Monthly!$B$2:$B$37,1,Monthly!G$2:G$37) | C5: =SUMIF(Monthly!$B$2:$B$37,2,Monthly!G$2:G$37) | D5: =SUMIF(Monthly!$B$2:$B$37,3,Monthly!G$2:G$37)
A6: Production commission | B6: =SUMIF(Monthly!$B$2:$B$37,1,Monthly!J$2:J$37) | C6: =SUMIF(Monthly!$B$2:$B$37,2,Monthly!J$2:J$37) | D6: =SUMIF(Monthly!$B$2:$B$37,3,Monthly!J$2:J$37)
A7: Sales commission | B7: =SUMIF(Monthly!$B$2:$B$37,1,Monthly!L$2:L$37) | C7: =SUMIF(Monthly!$B$2:$B$37,2,Monthly!L$2:L$37) | D7: =SUMIF(Monthly!$B$2:$B$37,3,Monthly!L$2:L$37)
A8: Manufacturer lead fees | B8: =SUMIF(Monthly!$B$2:$B$37,1,Monthly!M$2:M$37) | C8: =SUMIF(Monthly!$B$2:$B$37,2,Monthly!M$2:M$37) | D8: =SUMIF(Monthly!$B$2:$B$37,3,Monthly!M$2:M$37)
A9: Total revenue | B9: =SUMIF(Monthly!$B$2:$B$37,1,Monthly!N$2:N$37) | C9: =SUMIF(Monthly!$B$2:$B$37,2,Monthly!N$2:N$37) | D9: =SUMIF(Monthly!$B$2:$B$37,3,Monthly!N$2:N$37)
A10: AI cost | B10: =SUMIF(Monthly!$B$2:$B$37,1,Monthly!O$2:O$37) | C10: =SUMIF(Monthly!$B$2:$B$37,2,Monthly!O$2:O$37) | D10: =SUMIF(Monthly!$B$2:$B$37,3,Monthly!O$2:O$37)
A11: Payment costs | B11: =SUMIF(Monthly!$B$2:$B$37,1,Monthly!P$2:P$37) | C11: =SUMIF(Monthly!$B$2:$B$37,2,Monthly!P$2:P$37) | D11: =SUMIF(Monthly!$B$2:$B$37,3,Monthly!P$2:P$37)
A12: Marketing + ops (variable) | B12: =SUMIF(Monthly!$B$2:$B$37,1,Monthly!Q$2:Q$37) | C12: =SUMIF(Monthly!$B$2:$B$37,2,Monthly!Q$2:Q$37) | D12: =SUMIF(Monthly!$B$2:$B$37,3,Monthly!Q$2:Q$37)
A13: Fixed costs (hosting, marketing, team) | B13: =SUMIF(Monthly!$B$2:$B$37,1,Monthly!R$2:R$37) | C13: =SUMIF(Monthly!$B$2:$B$37,2,Monthly!R$2:R$37) | D13: =SUMIF(Monthly!$B$2:$B$37,3,Monthly!R$2:R$37)
A14: Total costs | B14: =SUMIF(Monthly!$B$2:$B$37,1,Monthly!S$2:S$37) | C14: =SUMIF(Monthly!$B$2:$B$37,2,Monthly!S$2:S$37) | D14: =SUMIF(Monthly!$B$2:$B$37,3,Monthly!S$2:S$37)
A15: Profit | B15: =SUMIF(Monthly!$B$2:$B$37,1,Monthly!T$2:T$37) | C15: =SUMIF(Monthly!$B$2:$B$37,2,Monthly!T$2:T$37) | D15: =SUMIF(Monthly!$B$2:$B$37,3,Monthly!T$2:T$37)
A16: Production run value we coordinate | B16: =SUMIF(Monthly!$B$2:$B$37,1,Monthly!I$2:I$37) | C16: =SUMIF(Monthly!$B$2:$B$37,2,Monthly!I$2:I$37) | D16: =SUMIF(Monthly!$B$2:$B$37,3,Monthly!I$2:I$37)
A17: Paying subscribers at year end | B17: =Monthly!F13 | C17: =Monthly!F25 | D17: =Monthly!F37
A18: Monthly revenue at year end | B18: =Monthly!N13 | C18: =Monthly!N25 | D18: =Monthly!N37

Sheet Assumptions
A1: Moko revenue model (draft, 27 Sep 2026). Yellow cells are inputs. Pick a scenario in B2.
A2: Scenario | B2: Base
A4: Assumption | B4: Low | C4: Base | D4: High | E4: Selected | F4: Unit | G4: Where it comes from
A5: New free sign-ups in month 1 | B5: 150 | C5: 300 | D5: 600 | E5: =INDEX(B5:D5,MATCH($B$2,$B$4:$D$4,0)) | F5: count | G5: Assumption: launch posts in maker communities
A6: Monthly sign-up growth, year 1 | B6: 0.1 | C6: 0.15 | D6: 0.2 | E6: =INDEX(B6:D6,MATCH($B$2,$B$4:$D$4,0)) | F6: % | G6: Assumption
A7: Monthly sign-up growth, year 2 | B7: 0.05 | C7: 0.08 | D7: 0.1 | E7: =INDEX(B7:D7,MATCH($B$2,$B$4:$D$4,0)) | F7: % | G7: Assumption
A8: Monthly sign-up growth, year 3 | B8: 0.03 | C8: 0.04 | D8: 0.05 | E8: =INDEX(B8:D8,MATCH($B$2,$B$4:$D$4,0)) | F8: % | G8: Assumption
A9: Free sign-ups who become paying subscribers | B9: 0.02 | C9: 0.04 | D9: 0.07 | E9: =INDEX(B9:D9,MATCH($B$2,$B$4:$D$4,0)) | F9: % | G9: Lenny's Newsletter: 3-5% good, 6-8% great for freemium self-serve
A10: Average subscription revenue per subscriber per month | B10: 22 | C10: 25 | D10: 27 | E10: =INDEX(B10:D10,MATCH($B$2,$B$4:$D$4,0)) | F10: $ | G10: $29/mo list, $19/mo yearly; blended
A11: Monthly subscriber churn | B11: 0.1 | C11: 0.07 | D11: 0.05 | E11: =INDEX(B11:D11,MATCH($B$2,$B$4:$D$4,0)) | F11: % | G11: Assumption for consumer/prosumer tools
A12: Share of subscribers placing a production run each month | B12: 0.02 | C12: 0.04 | D12: 0.06 | E12: =INDEX(B12:D12,MATCH($B$2,$B$4:$D$4,0)) | F12: % | G12: Assumption
A13: Average production run value | B13: 2000 | C13: 3000 | D13: 5000 | E13: =INDEX(B13:D13,MATCH($B$2,$B$4:$D$4,0)) | F13: $ | G13: Assumption: e.g. 250-500 units at $6-12
A14: Commission on production runs | B14: 0.05 | C14: 0.06 | D14: 0.08 | E14: =INDEX(B14:D14,MATCH($B$2,$B$4:$D$4,0)) | F14: % | G14: Assumption; Xometry marketplace gross margin is 34.7%
A15: Share of subscribers with a product on sale | B15: 0.1 | C15: 0.2 | D15: 0.3 | E15: =INDEX(B15:D15,MATCH($B$2,$B$4:$D$4,0)) | F15: % | G15: Assumption
A16: Monthly sales per selling creator | B16: 500 | C16: 800 | D16: 1500 | E16: =INDEX(B16:D16,MATCH($B$2,$B$4:$D$4,0)) | F16: $ | G16: Assumption
... A29: Support and coordination cost per production run | B29: 50 | C29: 50 | D29: 50 | E29: =INDEX(B29:D29,MATCH($B$2,$B$4:$D$4,0)) | F29: $ | G29: Assumption
A30: Hosting and tools per month, year 1 | B30: 300 | C30: 300 | D30: 300 | E30: =INDEX(B30:D30,MATCH($B$2,$B$4:$D$4,0)) | F30: $
A31: Hosting and tools per month, year 2 | B31: 1500 | C31: 1500 | D31: 1500 | E31: =INDEX(B31:D31,MATCH($B$2,$B$4:$D$4,0)) | F31: $
A32: Hosting and tools per month, year 3 | B32: 4000 | C32: 4000 | D32: 4000 | E32: =INDEX(B32:D32,MATCH($B$2,$B$4:$D$4,0)) | F32: $
A33: Fixed marketing per month, year 1 | B33: 1000 | C33: 1000 | D33: 1000 | E33: =INDEX(B33:D33,MATCH($B$2,$B$4:$D$4,0)) | F33: $
A34: Fixed marketing per month, year 2 | B34: 5000 | C34: 5000 | D34: 5000 | E34: =INDEX(B34:D34,MATCH($B$2,$B$4:$D$4,0)) | F34: $
A35: Fixed marketing per month, year 3 | B35: 15000 | C35: 15000 | D35: 15000 | E35: =INDEX(B35:D35,MATCH($B$2,$B$4:$D$4,0)) | F35: $
A36: Team cost per month, year 1 | B36: 0 | C36: 0 | D36: 0 | E36: =INDEX(B36:D36,MATCH($B$2,$B$4:$D$4,0)) | F36: $ | G36: Founders unpaid
A37: Team cost per month, year 2 | B37: 15000 | C37: 15000 | D37: 15000 | E37: =INDEX(B37:D37,MATCH($B$2,$B$4:$D$4,0)) | F37: $ | G37: 3 people at $60k
A38: Team cost per month, year 3 | B38: 30000 | C38: 30000 | D38: 30000 | E38: =INDEX(B38:D38,MATCH($B$2,$B$4:$D$4,0)) | F38: $ | G38: 6 people at $60k

Sheet Monthly
A1: Month | B1: Year | C1: Sign-up growth | D1: New free sign-ups | E1: New subscribers | F1: Subscribers | G1: Subscription revenue | H1: Production runs | I1: Production run value | J1: Production commission | K1: Sales through creators | L1: Sales commission | M1: Manufacturer lead fees | N1: Total revenue | O1: AI cost | P1: Payment costs | Q1: Marketing + ops (variable) | R1: Fixed costs | S1: Total costs | T1: Profit | U1: Cumulative profit
A2: 1 | B2: =INT((A2-1)/12)+1 | C2: =CHOOSE(B2,Assumptions!$E$6,Assumptions!$E$7,Assumptions!$E$8) | D2: =Assumptions!$E$5 | E2: =D2*Assumptions!$E$9 | F2: =E2 | G2: =F2*Assumptions!$E$10 | H2: =IF(A2>=Assumptions!$E$20,F2*Assumptions!$E$12,0) | I2: =H2*Assumptions!$E$13 | J2: =I2*Assumptions!$E$14 | K2: =IF(A2>=Assumptions!$E$21,F2*Assumptions!$E$15*Assumptions!$E$16,0) | L2: =K2*Assumptions!$E$17 | M2: =IF(A2>=Assumptions!$E$22,F2*Assumptions!$E$18*Assumptions!$E$19,0) | N2: =G2+J2+L2+M2 | O2: =D2*Assumptions!$E$23+F2*Assumptions!$E$24 | P2: =G2*Assumptions!$E$25+F2*Assumptions!$E$26+(J2+L2+M2)*Assumptions!$E$27 | Q2: =D2*Assumptions!$E$28+H2*Assumptions!$E$29 | R2: =CHOOSE(B2,Assumptions!$E$30,Assumptions!$E$31,Assumptions!$E$32)+CHOOSE(B2,Assumptions!$E$33,Assumptions!$E$34,Assumptions!$E$35)+CHOOSE(B2,Assumptions!$E$36,Assumptions!$E$37,Assumptions!$E$38) | S2: =O2+P2+Q2+R2 | T2: =N2-S2 | U2: =T2
A3: 2 | B3: =INT((A3-1)/12)+1 | C3: =CHOOSE(B3,Assumptions!$E$6,Assumptions!$E$7,Assumptions!$E$8) | D3: =D2*(1+C3) | E3: =D3*Assumptions!$E$9 | F3: =F2*(1-Assumptions!$E$11)+E3 | G3: =F3*Assumptions!$E$10 | H3: =IF(A3>=Assumptions!$E$20,F3*Assumptions!$E$12,0) | I3: =H3*Assumptions!$E$13 | J3: =I3*Assumptions!$E$14 | K3: =IF(A3>=Assumptions!$E$21,F3*Assumptions!$E$15*Assumptions!$E$16,0) | L3: =K3*Assumptions!$E$17 | M3: =IF(A3>=Assumptions!$E$22,F3*Assumptions!$E$18*Assumptions!$E$19,0) | N3: =G3+J3+L3+M3 | O3: =D3*Assumptions!$E$23+F3*Assumptions!$E$24 | P3: =G3*Assumptions!$E$25+F3*Assumptions!$E$26+(J3+L3+M3)*Assumptions!$E$27 | Q3: =D3*Assumptions!$E$28+H3*Assumptions!$E$29 | R3: =CHOOSE(B3,Assumptions!$E$30,Assumptions!$E$31,Assumptions!$E$32)+CHOOSE(B3,Assumptions!$E$33,Assumptions!$E$34,Assumptions!$E$35)+CHOOSE(B3,Assumptions!$E$36,Assumptions!$E$37,Assumptions!$E$38) | S3: =O3+P3+Q3+R3 | T3: =N3-S3 | U3: =U2+T3
A4: 3 | B4: =INT((A4-1)/12)+1 | C4: =CHOOSE(B4,Assumptions!$E$6,Assumptions!$E$7,Assumptions!$E$8) | D4: =D3*(1+C4) | E4: =D4*Assumptions!$E$9 | F4: =F3*(1-Assumptions!$E$11)+E4 | G4: =F4*Assumptions!$E$10 | H4: =IF(A4>=Assumptions!$E$20,F4*Assumptions!$E$12,0) | I4: =H4*Assumptions!$E$13 | J4: =I4*Assumptions!$E$14 | K4: =IF(A4>=Assumptions!$E$21,F4*Assumptions!$E$15*Assumptions!$E$16,0) | L4: =K4*Assumptions!$E$17 | M4: =IF(A4>=Assumptions!$E$22,F4*Assumptions!$E$18*Assumptions!$E$19,0) | N4: =G4+J4+L4+M4 | O4: =D4*Assumptions!$E$23+F4*Assumptions!$E$24 | P4: =G4*Assumptions!$E$25+F4*Assumptions!$E$26+(J4+L4+M4)*Assumptions!$E$27 | Q4: =D4*Assumptions!$E$28+H4*Assumptions!$E$29 | R4: =CHOOSE(B4,Assumptions!$E$30,Assumptions!$E$31,Assumptions!$E$32)+CHOOSE(B4,Assumptions!$E$33,Assumptions!$E$34,Assumptions!$E$35)+CHOOSE(B4,Assumptions!$E$36,Assumptions!$E$37,Assumptions!$E$38) | S4: =O4+P4+Q4+R4 | T4: =N4-S4 | U4: =U3+T4
A5: 4 | B5: =INT((A5-1)/12)+1 | C5: =CHOOSE(B5,Assumptions!$E$6,Assumptions!$E$7,Assumptions!$E$8) | D5: =D4*(1+C5) | E5: =D5*Assumptions!$E$9 | F5: =F4*(1-Assumptions!$E$11)+E5 | G5: =F5*Assumptions!$E$10 | H5: =IF(A5>=Assumptions!$E$20,F5*Assumptions!$E$12,0) | I5: =H5*Assumptions!$E$13 | J5: =I5*Assumptions!$E$14 | K5: =IF(A5>=Assumptions!$E$21,F5*Assumptions!$E$15*Assumptions!$E$16,0) | L5: =K5*Assumptions!$E$17 | M5: =IF(A5>=Assumptions!$E$22,F5*Assumptions!$E$18*Assumptions!$E$19,0) | N5: =G5+J5+L5+M5 | O5: =D5*Assumptions!$E$23+F5*Assumptions!$E$24 | P5: =G5*Assumptions!$E$25+F5*Assumptions!$E$26+(J5+L5+M5)*Assumptions!$E$27 | Q5: =D5*Assumptions!$E$28+H5*Assumptions!$E$29 | R5: =CHOOSE(B5,Assumptions!$E$30,Assumptions!$E$31,Assumptions!$E$32)+CHOOSE(B5,Assumptions!$E$33,Assumptions!$E$34,Assumptions!$E$35)+CHOOSE(B5,Assumptions!$E$36,Assumptions!$E$37,Assumptions!$E$38) | S5: =O5+P5+Q5+R5 | T5: =N5-S5 | U5: =U4+T5
A6: 5 | B6: =INT((A6-1)/12)+1 | C6: =CHOOSE(B6,Assumptions!$E$6,Assumptions!$E$7,Assumptions!$E$8) | D6: =D5*(1+C6) | E6: =D6*Assumptions!$E$9 | F6: =F5*(1-Assumptions!$E$11)+E6 | G6: =F6*Assumptions!$E$10 | H6: =IF(A6>=Assumptions!$E$20,F6*Assumptions!$E$12,0) | I6: =H6*Assumptions!$E$13 | J6: =I6*Assumptions!$E$14 | K6: =IF(A6>=Assumptions!$E$21,F6*Assumptions!$E$15*Assumptions!$E$16,0) | L6: =K6*Assumptions!$E$17 | M6: =IF(A6>=Assumptions!$E$22,F6*Assumptions!$E$18*Assumptions!$E$19,0) | N6: =G6+J6+L6+M6 | O6: =D6*Assumptions!$E$23+F6*Assumptions!$E$24 | P6: =G6*Assumptions!$E$25+F6*Assumptions!$E$26+(J6+L6+M6)*Assumptions!$E$27 | Q6: =D6*Assumptions!$E$28+H6*Assumptions!$E$29 | R6: =CHOOSE(B6,Assumptions!$E$30,Assumptions!$E$31,Assumptions!$E$32)+CHOOSE(B6,Assumptions!$E$33,Assumptions!$E$34,Assumptions!$E$35)+CHOOSE(B6,Assumptions!$E$36,Assumptions!$E$37,Assumptions!$E$38) | S6: =O6+P6+Q6+R6 | T6: =N6-S6 | U6: =U5+T6
A7: 6 | B7: =INT((A7-1)/12)+1 | C7: =CHOOSE(B7,Assumptions!$E$6,Assumptions!$E$7,Assumptions!$E$8) | D7: =D6*(1+C7) | E7: =D7*Assumptions!$E$9 | F7: =F6*(1-Assumptions!$E$11)+E7 | G7: =F7*Assumptions!$E$10 | H7: =IF(A7>=Assumptions!$E$20,F7*Assumptions!$E$12,0) | I7: =H7*Assumptions!$E$13 | J7: =I7*Assumptions!$E$14 | K7: =IF(A7>=Assumptions!$E$21,F7*Assumptions!$E$15*Assumptions!$E$16,0) | L7: =K7*Assumptions!$E$17 | M7: =IF(A7>=Assumptions!$E$22,F7*Assumptions!$E$18*Assumptions!$E$19,0) | N7: =G7+J7+L7+M7 | O7: =D7*Assumptions!$E$23+F7*Assumptions!$E$24 | P7: =G7*Assumptions!$E$25+F7*Assumptions!$E$26+(J7+L7+M7)*Assumptions!$E$27 | Q7: =D7*Assumptions!$E$28+H7*Assumptions!$E$29 | R7: =CHOOSE(B7,Assumptions!$E$30,Assumptions!$E$31,Assumptions!$E$32)+CHOOSE(B7,Assumptions!$E$33,Assumptions!$E$34,Assumptions!$E$35)+CHOOSE(B7,Assumptions!$E$36,Assumptions!$E$37,Assumptions!$E$38) | S7: =O7+P7+Q7+R7 | T7: =N7-S7 | U7: =U6+T7
A8: 7 | B8: =INT((A8-1)/12)+1 | C8: =CHOOSE(B8,Assumptions!$E$6,Assumptions!$E$7,Assumptions!$E$8) | D8: =D7*(1+C8) | E8: =D8*Assumptions!$E$9 | F8: =F7*(1-Assumptions!$E$11)+E8 | G8: =F8*Assumptions!$E$10 | H8: =IF(A8>=Assumptions!$E$20,F8*Assumptions!$E$12,0) | I8: =H8*Assumptions!$E$13 | J8: =I8*Assumptions!$E$14 | K8: =IF(A8>=Assumptions!$E$21,F8*Assumptions!$E$15*Assumptions!$E$16,0) | L8: =K8*Assumptions!$E$17 | M8: =IF(A8>=Assumptions!$E$22,F8*Assumptions!$E$18*Assumptions!$E$19,0) | N8: =G8+J8+L8+M8 | O8: =D8*Assumptions!$E$23+F8*Assumptions!$E$24 | P8: =G8*Assumptions!$E$25+F8*Assumptions!$E$26+(J8+L8+M8)*Assumptions!$E$27 | Q8: =D8*Assumptions!$E$28+H8*Assumptions!$E$29 | R8: =CHOOSE(B8,Assumptions!$E$30,Assumptions!$E$31,Assumptions!$E$32)+CHOOSE(B8,Assumptions!$E$33,Assumptions!$E$34,Assumptions!$E$35)+CHOOSE(B8,Assumptions!$E$36,Assumptions!$E$37,Assumptions!$E$38) | S8: =O8+P8+Q8+R8 | T8: =N8-S8 | U8: =U7+T8
A9: 8 | B9: =INT((A9-1)/12)+1 | C9: =CHOOSE(B9,Assumptions!$E$6,Assumptions!$E$7,Assumptions!$E$8) | D9: =D8*(1+C9) | E9: =D9*Assumptions!$E$9 | F9: =F8*(1-Assumptions!$E$11)+E9 | G9: =F9*Assumptions!$E$10 | H9: =IF(A9>=Assumptions!$E$20,F9*Assumptions!$E$12,0) | I9: =H9*Assumptions!$E$13 | J9: =I9*Assumptions!$E$14 | K9: =IF(A9>=Assumptions!$E$21,F9*Assumptions!$E$15*Assumptions!$E$16,0) | L9: =K9*Assumptions!$E$17 | M9: =IF(A9>=Assumptions!$E$22,F9*Assumptions!$E$18*Assumptions!$E$19,0) | N9: =G9+J9+L9+M9 | O9: =D9*Assumptions!$E$23+F9*Assumptions!$E$24 | P9: =G9*Assumptions!$E$25+F9*Assumptions!$E$26+(J9+L9+M9)*Assumptions!$E$27 | Q9: =D9*Assumptions!$E$28+H9*Assumptions!$E$29 | R9: =CHOOSE(B9,Assumptions!$E$30,Assumptions!$E$31,Assumptions!$E$32)+CHOOSE(B9,Assumptions!$E$33,Assumptions!$E$34,Assumptions!$E$35)+CHOOSE(B9,Assumptions!$E$36,Assumptions!$E$37,Assumptions!$E$38) | S9: =O9+P9+Q9+R9 | T9: =N9-S9 | U9: =U8+T9
A10: 9 | B10: =INT((A10-1)/12)+1 | C10: =CHOOSE(B10,Assumptions!$E$6,Assumptions!$E$7,Assumptions!$E$8) | D10: =D9*(1+C10) | E10: =D10*Assumptions!$E$9 | F10: =F9*(1-Assumptions!$E$11)+E10 | G10: =F10*Assumptions!$E$10 | H10: =IF(A10>=Assumptions!$E$20,F10*Assumptions!$E$12,0) | I10: =H10*Assumptions!$E$13 | J10: =I10*Assumptions!$E$14 | K10: =IF(A10>=Assumptions!$E$21,F10*Assumptions!$E$15*Assumptions!$E$16,0) | L10: =K10*Assumptions!$E$17 | M10: =IF(A10>=Assumptions!$E$22,F10*Assumptions!$E$18*Assumptions!$E$19,0) | N10: =G10+J10+L10+M10 | O10: =D10*Assumptions!$E$23+F10*Assumptions!$E$24 | P10: =G10*Assumptions!$E$25+F10*Assumptions!$E$26+(J10+L10+M10)*Assumptions!$E$27 | Q10: =D10*Assumptions!$E$28+H10*Assumptions!$E$29 | R10: =CHOOSE(B10,Assumptions!$E$30,Assumptions!$E$31,Assumptions!$E$32)+CHOOSE(B10,Assumptions!$E$33,Assumptions!$E$34,Assumptions!$E$35)+CHOOSE(B10,Assumptions!$E$36,Assumptions!$E$37,Assumptions!$E$38) | S10: =O10+P10+Q10+R10 | T10: =N10-S10 | U10: =U9+T10
A11: 10 | B11: =INT((A11-1)/12)+1 | C11: =CHOOSE(B11,Assumptions!$E$6,Assumptions!$E$7,Assumptions!$E$8) | D11: =D10*(1+C11) | E11: =D11*Assumptions!$E$9 | F11: =F10*(1-Assumptions!$E$11)+E11 | G11: =F11*Assumptions!$E$10 | H11: =IF(A11>=Assumptions!$E$20,F11*Assumptions!$E$12,0) | I11: =H11*Assumptions!$E$13 | J11: =I11*Assumptions!$E$14 | K11: =IF(A11>=Assumptions!$E$21,F11*Assumptions!$E$15*Assumptions!$E$16,0) | L11: =K11*Assumptions!$E$17 | M11: =IF(A11>=Assumptions!$E$22,F11*Assumptions!$E$18*Assumptions!$E$19,0) | N11: =G11+J11+L11+M11 | O11: =D11*Assumptions!$E$23+F11*Assumptions!$E$24 | P11: =G11*Assumptions!$E$25+F11*Assumptions!$E$26+(J11+L11+M11)*Assumptions!$E$27 | Q11: =D11*Assumptions!$E$28+H11*Assumptions!$E$29 | R11: =CHOOSE(B11,Assumptions!$E$30,Assumptions!$E$31,Assumptions!$E$32)+CHOOSE(B11,Assumptions!$E$33,Assumptions!$E$34,Assumptions!$E$35)+CHOOSE(B11,Assumptions!$E$36,Assumptions!$E$37,Assumptions!$E$38) | S11: =O11+P11+Q11+R11 | T11: =N11-S11 | U11: =U10+T11
A12: 11 | B12: =INT((A12-1)/12)+1 | C12: =CHOOSE(B12,Assumptions!$E$6,Assumptions!$E$7,Assumptions!$E$8) | D12: =D11*(1+C12) | E12: =D12*Assumptions!$E$9 | F12: =F11*(1-Assumptions!$E$11)+E12 | G12: =F12*Assumptions!$E$10 | H12: =IF(A12>=Assumptions!$E$20,F12*Assumptions!$E$12,0) | I12: =H12*Assumptions!$E$13 | J12: =I12*Assumptions!$E$14 | K12: =IF(A12>=Assumptions!$E$21,F12*Assumptions!$E$15*Assumptions!$E$16,0) | L12: =K12*Assumptions!$E$17 | M12: =IF(A12>=Assumptions!$E$22,F12*Assumptions!$E$18*Assumptions!$E$19,0) | N12: =G12+J12+L12+M12 | O12: =D12*Assumptions!$E$23+F12*Assumptions!$E$24 | P12: =G12*Assumptions!$E$25+F12*Assumptions!$E$26+(J12+L12+M12)*Assumptions!$E$27 | Q12: =D12*Assumptions!$E$28+H12*Assumptions!$E$29 | R12: =CHOOSE(B12,Assumptions!$E$30,Assumptions!$E$31,Assumptions!$E$32)+CHOOSE(B12,Assumptions!$E$33,Assumptions!$E$34,Assumptions!$E$35)+CHOOSE(B12,Assumptions!$E$36,Assumptions!$E$37,Assumptions!$E$38) | S12: =O12+P12+Q12+R12 | T12: =N12-S12 | U12: =U11+T12
A13: 12 | B13: =INT((A13-1)/12)+1 | C13: =CHOOSE(B13,Assumptions!$E$6,Assumptions!$E$7,Assumptions!$E$8) | D13: =D12*(1+C13) | E13: =D13*Assumptions!$E$9 | F13: =F12*(1-Assumptions!$E$11)+E13 | G13: =F13*Assumptions!$E$10 | H13: =IF(A13>=Assumptions!$E$20,F13*Assumptions!$E$12,0) | I13: =H13*Assumptions!$E$13 | J13: =I13*Assumptions!$E$14 | K13: =IF(A13>=Assumptions!$E$21,F13*Assumptions!$E$15*Assumptions!$E$16,0) | L13: =K13*Assumptions!$E$17 | M13: =IF(A13>=Assumptions!$E$22,F13*Assumptions!$E$18*Assumptions!$E$19,0) | N13: =G13+J13+L13+M13 | O13: =D13*Assumptions!$E$23+F13*Assumptions!$E$24 | P13: =G13*Assumptions!$E$25+F13*Assumptions!$E$26+(J13+L13+M13)*Assumptions!$E$27 | Q13: =D13*Assumptions!$E$28+H13*Assumptions!$E$29 | R13: =CHOOSE(B13,Assumptions!$E$30,Assumptions!$E$31,Assumptions!$E$32)+CHOOSE(B13,Assumptions!$E$33,Assumptions!$E$34,Assumptions!$E$35)+CHOOSE(B13,Assumptions!$E$36,Assumptions!$E$37,Assumptions!$E$38) | S13: =O13+P13+Q13+R13 | T13: =N13-S13 | U13: =U12+T13
A14: 13 | B14: =INT((A14-1)/12)+1 | C14: =CHOOSE(B14,Assumptions!$E$6,Assumptions!$E$7,Assumptions!$E$8) | D14: =D13*(1+C14) | E14: =D14*Assumptions!$E$9 | F14: =F13*(1-Assumptions!$E$11)+E14 | G14: =F14*Assumptions!$E$10 | H14: =IF(A14>=Assumptions!$E$20,F14*Assumptions!$E$12,0) | I14: =H14*Assumptions!$E$13 | J14: =I14*Assumptions!$E$14 | K14: =IF(A14>=Assumptions!$E$21,F14*Assumptions!$E$15*Assumptions!$E$16,0) | L14: =K14*Assumptions!$E$17 | M14: =IF(A14>=Assumptions!$E$22,F14*Assumptions!$E$18*Assumptions!$E$19,0) | N14: =G14+J14+L14+M14 | O14: =D14*Assumptions!$E$23+F14*Assumptions!$E$24 | P14: =G14*Assumptions!$E$25+F14*Assumptions!$E$26+(J14+L14+M14)*Assumptions!$E$27 | Q14: =D14*Assumptions!$E$28+H14*Assumptions!$E$29 | R14: =CHOOSE(B14,Assumptions!$E$30,Assumptions!$E$31,Assumptions!$E$32)+CHOOSE(B14,Assumptions!$E$33,Assumptions!$E$34,Assumptions!$E$35)+CHOOSE(B14,Assumptions!$E$36,Assumptions!$E$37,Assumptions!$E$38) | S14: =O14+P14+Q14+R14 | T14: =N14-S14 | U14: =U13+T14
... A37: 36 | B37: =INT((A37-1)/12)+1 | C37: =CHOOSE(B37,Assumptions!$E$6,Assumptions!$E$7,Assumptions!$E$8) | D37: =D36*(1+C37) | E37: =D37*Assumptions!$E$9 | F37: =F36*(1-Assumptions!$E$11)+E37 | G37: =F37*Assumptions!$E$10 | H37: =IF(A37>=Assumptions!$E$20,F37*Assumptions!$E$12,0) | I37: =H37*Assumptions!$E$13 | J37: =I37*Assumptions!$E$14 | K37: =IF(A37>=Assumptions!$E$21,F37*Assumptions!$E$15*Assumptions!$E$16,0) | L37: =K37*Assumptions!$E$17 | M37: =IF(A37>=Assumptions!$E$22,F37*Assumptions!$E$18*Assumptions!$E$19,0) | N37: =G37+J37+L37+M37 | O37: =D37*Assumptions!$E$23+F37*Assumptions!$E$24 | P37: =G37*Assumptions!$E$25+F37*Assumptions!$E$26+(J37+L37+M37)*Assumptions!$E$27 | Q37: =D37*Assumptions!$E$28+H37*Assumptions!$E$29 | R37: =CHOOSE(B37,Assumptions!$E$30,Assumptions!$E$31,Assumptions!$E$32)+CHOOSE(B37,Assumptions!$E$33,Assumptions!$E$34,Assumptions!$E$35)+CHOOSE(B37,Assumptions!$E$36,Assumptions!$E$37,Assumptions!$E$38) | S37: =O37+P37+Q37+R37 | T37: =N37-S37 | U37: =U36+T37

Sheet All scenarios
A1: Values computed for all three scenarios with the default assumptions (static; the Summary sheet recalculates for the selected one).
A3: Scenario | B3: Year | C3: Sign-ups | D3: Subscribers (end) | E3: Revenue | F3: Costs | G3: Profit | H3: Monthly revenue (end)
A4: Low | B4: 1 | C4: 3208 | D4: 43 | E4: 6015 | F4: 24254 | G4: -18239 | H4: 1028
A5: Low | B5: 2 | C5: 7153 | D5: 103 | E5: 23526 | F5: 278793 | G5: -255267 | H5: 2775
A6: Low | B6: 3 | C6: 11235 | D6: 168 | E6: 44752 | F6: 621739 | G6: -576987 | H6: 4543
A7: Base | B7: 1 | C7: 8701 | D7: 269 | E7: 42900 | F7: 43158 | G7: -258 | H7: 8662
A8: Base | B8: 2 | C8: 28606 | D8: 957 | E8: 285420 | F8: 366045 | G8: -80624 | H8: 39219
A9: Base | B9: 3 | C9: 54923 | D9: 1972 | E9: 733597 | F9: 818314 | G9: -84717 | H9: 80855
A10: High | B10: 1 | C10: 23748 | D10: 1407 | E10: 304374 | F10: 112597 | G10: 191777 | H10: 71763
A11: High | B11: 2 | C11: 104865 | D11: 6706 | E11: 3463575 | F11: 856849 | G11: 2606726 | H11: 523064
A12: High | B12: 3 | C12: 233836 | D12: 16535 | E12: 10968771 | F12: 2219786 | G12: 8748985 | H12: 1289701
